snoopy/__init__.py
snoopy/hello.py
HiSnoopy-0.0.2.dist-info/METADATA
HiSnoopy-0.0.2.dist-info/WHEEL
HiSnoopy-0.0.2.dist-info/top_level.txt
HiSnoopy-0.0.2.dist-info/RECORD
