Metadata-Version: 2.1
Name: HiSnoopy
Version: 0.0.2
Summary: Say hi lib
Home-page: UNKNOWN
Author: Przemyslaw Zaradzki
Author-email: <przemyslaw.zaradzki@wp.pl>
License: UNKNOWN
Keywords: python
Platform: UNKNOWN
Classifier: Development Status :: 1 - Planning
Classifier: Intended Audience :: Developers
Classifier: Programming Language :: Python :: 3
Classifier: Operating System :: Unix
Classifier: Operating System :: MacOS :: MacOS X
Classifier: Operating System :: Microsoft :: Windows
